flytekitplugins/dgxc_lepton/__init__.py
flytekitplugins/dgxc_lepton/config.py
flytekitplugins/dgxc_lepton/connector.py
flytekitplugins/dgxc_lepton/task.py
flytekitplugins_dgxc_lepton-1.16.12.dist-info/METADATA
flytekitplugins_dgxc_lepton-1.16.12.dist-info/WHEEL
flytekitplugins_dgxc_lepton-1.16.12.dist-info/entry_points.txt
flytekitplugins_dgxc_lepton-1.16.12.dist-info/top_level.txt
flytekitplugins_dgxc_lepton-1.16.12.dist-info/RECORD
